<!--
Copyright 2011-2013 Normation SAS

This program is free software: you can redistribute it and/or modify
it under the terms of the GNU General Public License as published by
the Free Software Foundation, Version 3.

This program is distributed in the hope that it will be useful,
but WITHOUT ANY WARRANTY; without even the implied warranty of
MERCHANTABILITY or FITNESS FOR A PARTICULAR PURPOSE.  See the
GNU General Public License for more details.

You should have received a copy of the GNU General Public License
along with this program.  If not, see <http://www.gnu.org/licenses/>.
-->

<TECHNIQUE name="Set the permissions on files">
  <DESCRIPTION>Set the permissions on files</DESCRIPTION>

  <MULTIINSTANCE>true</MULTIINSTANCE>
  <BUNDLES>
    <NAME>files_permissions</NAME>
  </BUNDLES>

  <TMLS>
    <TML name="filesPermissions"/>
    <TML name="permlist">
      <INCLUDED>false</INCLUDED>
      <OUTPATH>filesPermissions/permlist</OUTPATH>
    </TML>
  </TMLS>

  <COMPATIBLE>
    <OS version=">= 5">Debian</OS>
    <OS version=">= 4 (Nahant)">RHEL / CentOS</OS>
    <OS version=">= 10 SP1 (Agama Lizard)">SuSE LES / DES / OpenSuSE</OS>
    <AGENT version=">= 3.1.5">CFengine community</AGENT>
  </COMPATIBLE>

  <TRACKINGVARIABLE>
    <SAMESIZEAS>FILEPERMISSION_FILENAME</SAMESIZEAS>
  </TRACKINGVARIABLE>

  <SECTIONS>
    <SECTION name="File permissions" multivalued="true" component="true" componentKey="FILEPERMISSION_FILENAME">
      <INPUT>
        <NAME>FILEPERMISSION_FILENAME</NAME>
        <DESCRIPTION>File to set permissions on</DESCRIPTION>
      </INPUT>
      <INPUT>
        <NAME>FILEPERMISSION_IGNORE_ABSENTFILE</NAME>
        <DESCRIPTION>Ignore file or directory if it does not exist</DESCRIPTION>
        <CONSTRAINT>
          <TYPE>boolean</TYPE>
          <DEFAULT>false</DEFAULT>
        </CONSTRAINT>
      </INPUT>
      <INPUT>
        <NAME>FILEPERMISSION_RECURSION</NAME>
        <DESCRIPTION>In case the path is a directory, the permissions should be adjusted recursively</DESCRIPTION>
        <CONSTRAINT>
          <TYPE>boolean</TYPE>
          <DEFAULT>false</DEFAULT>
        </CONSTRAINT>
      </INPUT>
      <INPUT>
        <NAME>FILEPERMISSION_EDITUSER</NAME>
        <DESCRIPTION>Set file owner?</DESCRIPTION>
        <CONSTRAINT>
          <TYPE>boolean</TYPE>
          <DEFAULT>false</DEFAULT>
        </CONSTRAINT>
      </INPUT>
      <INPUT>
        <NAME>FILEPERMISSION_USER</NAME>
        <DESCRIPTION>File owner</DESCRIPTION>
        <CONSTRAINT>
          <MAYBEEMPTY>true</MAYBEEMPTY>
        </CONSTRAINT>
      </INPUT>
      <INPUT>
        <NAME>FILEPERMISSION_EDITGROUP</NAME>
        <DESCRIPTION>Set file group?</DESCRIPTION>
        <CONSTRAINT>
          <TYPE>boolean</TYPE>
          <DEFAULT>false</DEFAULT>
        </CONSTRAINT>
      </INPUT>
      <INPUT>
        <NAME>FILEPERMISSION_GROUP</NAME>
        <DESCRIPTION>File group</DESCRIPTION>
        <CONSTRAINT>
          <MAYBEEMPTY>true</MAYBEEMPTY>
        </CONSTRAINT>
      </INPUT>
      <INPUT>
        <NAME>FILEPERMISSION_EDITMODE</NAME>
        <DESCRIPTION>Set file permissions?</DESCRIPTION>
        <CONSTRAINT>
          <TYPE>boolean</TYPE>
          <DEFAULT>false</DEFAULT>
        </CONSTRAINT>
      </INPUT>
      <INPUT>
        <NAME>FILEPERMISSION_MODE</NAME>
        <DESCRIPTION>File permissions</DESCRIPTION>
        <CONSTRAINT>
          <TYPE>perm</TYPE>
          <MAYBEEMPTY>true</MAYBEEMPTY>
        </CONSTRAINT>
      </INPUT>
      <INPUT>
        <NAME>FILEPERMISSION_SUID</NAME>
        <DESCRIPTION>Set SetUID bit?</DESCRIPTION>
        <CONSTRAINT>
          <TYPE>boolean</TYPE>
          <DEFAULT>false</DEFAULT>
        </CONSTRAINT>
      </INPUT>
      <INPUT>
        <NAME>FILEPERMISSION_SGID</NAME>
        <DESCRIPTION>Set SetGID bit?</DESCRIPTION>
        <LONGDESCRIPTION>Note: The SetUID and SetGID bits will not be applied recursively, for obvious security reasons.</LONGDESCRIPTION>
        <CONSTRAINT>
          <TYPE>boolean</TYPE>
          <DEFAULT>false</DEFAULT>
        </CONSTRAINT>
      </INPUT>
    </SECTION>
  </SECTIONS>

</TECHNIQUE>
